deepspeech/__init__.py
deepspeech/_impl.cpython-39-darwin.so
deepspeech/client.py
deepspeech/impl.py
deepspeech/lib/libdeepspeech.so
deepspeech-0.9.3.dist-info/METADATA
deepspeech-0.9.3.dist-info/WHEEL
deepspeech-0.9.3.dist-info/entry_points.txt
deepspeech-0.9.3.dist-info/top_level.txt
deepspeech-0.9.3.dist-info/RECORD
